unisafe/__init__.py
unisafe/uread.py
unisafe/wrappers.py
unisafe/parse/__init__.py
unisafe/parse/dammit.py
unisafe-0.1.0.dist-info/LICENSE
unisafe-0.1.0.dist-info/METADATA
unisafe-0.1.0.dist-info/WHEEL
unisafe-0.1.0.dist-info/top_level.txt
unisafe-0.1.0.dist-info/RECORD
