Metadata-Version: 2.1
Name: unisafe
Version: 0.1.0
Summary: Read text files with unknown or mixed encodings into UTF-8.
Home-page: https://github.com/ionite34/unisafe
Author: ionite
Author-email: dev@ionite.io
License: MIT
Classifier: Programming Language :: Python :: 3
Classifier: Programming Language :: Python :: 3 :: Only
Classifier: Programming Language :: Python :: 3.7
Classifier: Programming Language :: Python :: 3.8
Classifier: Programming Language :: Python :: 3.9
Classifier: Programming Language :: Python :: 3.10
Requires-Python: >=3.7
License-File: LICENSE
Requires-Dist: beautifulsoup4 (~=4.11.1)
Requires-Dist: cchardet (~=2.1.7)
